{
  "extends": "tslint:latest",
  "rules": {
    "object-literal-sort-keys": false,
    "ordered-imports": false,
    "one-line": false,
    "space-within-parens": false,
    "no-var-requires": false,
    "trailing-comma": [true, {"multiline": "never", "singleline": "never"}],
    "no-submodule-imports": [
      true,
      "csv-parse/lib/sync"
    ],
    "max-line-length": [
      true,
      150
    ],
    "no-magic-numbers": [
      true,
      -1,
      0,
      1,
      2
    ],
    "no-consecutive-blank-lines": [
      true,
      2
    ],
    "prefer-conditional-expression": false,
    "indent": [true, "spaces", 4],
    "whitespace": [true, "check-module"]
  },
  "type-check": true
}
